{
  "entrypoints": [
    "main"
  ],
  "origins": {
    "237": [
      237
    ],
    "668": [
      61,
      401,
      869,
      668
    ],
    "17896441": [
      668,
      869,
      401
    ],
    "76634496": [
      640
    ],
    "main": [
      354,
      869,
      792
    ],
    "runtime~main": [
      792,
      869,
      354
    ],
    "065e901c": [
      380
    ],
    "0d502caa": [
      583
    ],
    "0e384e19": [
      976
    ],
    "0fcb4221": [
      771
    ],
    "14eb3368": [
      869,
      969
    ],
    "1933a263": [
      679
    ],
    "1bf877d8": [
      234
    ],
    "1d5c927d": [
      52
    ],
    "1df93b7f": [
      869,
      964
    ],
    "1f391b9e": [
      668,
      869,
      61
    ],
    "23bbaa4d": [
      628
    ],
    "2779c114": [
      381
    ],
    "393be207": [
      134
    ],
    "3bdcc6ea": [
      138
    ],
    "4da0cc27": [
      247
    ],
    "5014eec9": [
      501
    ],
    "5e95c892": [
      647
    ],
    "6245a28e": [
      994
    ],
    "642eca8e": [
      491
    ],
    "6908b1b0": [
      762
    ],
    "6b1ba41c": [
      845
    ],
    "74e04c72": [
      445
    ],
    "74f6f9f9": [
      818
    ],
    "7694d7e1": [
      610
    ],
    "84a15b3e": [
      748
    ],
    "9a90c0e7": [
      175
    ],
    "a2ba2a64": [
      732
    ],
    "a3208752": [
      443
    ],
    "a35772e5": [
      646
    ],
    "a6d26dbd": [
      432
    ],
    "a7456010": [
      235
    ],
    "a7bd4aaa": [
      98
    ],
    "a94703ab": [
      869,
      48
    ],
    "aba21aa0": [
      742
    ],
    "b2b450a7": [
      250
    ],
    "b420b19e": [
      806
    ],
    "c2a49136": [
      882
    ],
    "c6f57b75": [
      624
    ],
    "c85a4240": [
      490
    ],
    "f6310cba": [
      775
    ],
    "f7d327e6": [
      725
    ],
    "fdcb31b2": [
      262
    ],
    "styles": [
      48,
      61,
      354,
      401,
      668,
      792,
      964,
      969,
      869
    ]
  },
  "assets": {
    "48": {
      "js": [
        {
          "file": "assets/js/a94703ab.643e6934.js",
          "hash": "74caa70f6c914367",
          "publicPath": "/microservices-datadriven/obaas/assets/js/a94703ab.643e6934.js"
        }
      ]
    },
    "52": {
      "js": [
        {
          "file": "assets/js/1d5c927d.69dbad56.js",
          "hash": "664001eddf7a3f04",
          "publicPath": "/microservices-datadriven/obaas/assets/js/1d5c927d.69dbad56.js"
        }
      ]
    },
    "61": {
      "js": [
        {
          "file": "assets/js/1f391b9e.d091afa4.js",
          "hash": "61365aab88dde4d6",
          "publicPath": "/microservices-datadriven/obaas/assets/js/1f391b9e.d091afa4.js"
        }
      ]
    },
    "98": {
      "js": [
        {
          "file": "assets/js/a7bd4aaa.2ca06876.js",
          "hash": "3b5630d91ed7861b",
          "publicPath": "/microservices-datadriven/obaas/assets/js/a7bd4aaa.2ca06876.js"
        }
      ]
    },
    "134": {
      "js": [
        {
          "file": "assets/js/393be207.80eb0ba2.js",
          "hash": "daaa03cdd6776013",
          "publicPath": "/microservices-datadriven/obaas/assets/js/393be207.80eb0ba2.js"
        }
      ]
    },
    "138": {
      "js": [
        {
          "file": "assets/js/3bdcc6ea.e8197310.js",
          "hash": "b5468dcef26ba5f5",
          "publicPath": "/microservices-datadriven/obaas/assets/js/3bdcc6ea.e8197310.js"
        }
      ]
    },
    "175": {
      "js": [
        {
          "file": "assets/js/9a90c0e7.6f93064f.js",
          "hash": "f05211354f4b8a69",
          "publicPath": "/microservices-datadriven/obaas/assets/js/9a90c0e7.6f93064f.js"
        }
      ]
    },
    "234": {
      "js": [
        {
          "file": "assets/js/1bf877d8.a1817167.js",
          "hash": "7e77539dc3e01965",
          "publicPath": "/microservices-datadriven/obaas/assets/js/1bf877d8.a1817167.js"
        }
      ]
    },
    "235": {
      "js": [
        {
          "file": "assets/js/a7456010.25370a92.js",
          "hash": "b8dadc090f401680",
          "publicPath": "/microservices-datadriven/obaas/assets/js/a7456010.25370a92.js"
        }
      ]
    },
    "237": {
      "js": [
        {
          "file": "assets/js/237.d496122d.js",
          "hash": "fb5dc56050a66405",
          "publicPath": "/microservices-datadriven/obaas/assets/js/237.d496122d.js"
        }
      ]
    },
    "247": {
      "js": [
        {
          "file": "assets/js/4da0cc27.4bc4e1e7.js",
          "hash": "2af8a32ec394c82a",
          "publicPath": "/microservices-datadriven/obaas/assets/js/4da0cc27.4bc4e1e7.js"
        }
      ]
    },
    "250": {
      "js": [
        {
          "file": "assets/js/b2b450a7.841bc4b6.js",
          "hash": "38649817734919c8",
          "publicPath": "/microservices-datadriven/obaas/assets/js/b2b450a7.841bc4b6.js"
        }
      ]
    },
    "262": {
      "js": [
        {
          "file": "assets/js/fdcb31b2.e396bc9e.js",
          "hash": "bf539c8cb964eaf0",
          "publicPath": "/microservices-datadriven/obaas/assets/js/fdcb31b2.e396bc9e.js"
        }
      ]
    },
    "354": {
      "js": [
        {
          "file": "assets/js/runtime~main.285401bd.js",
          "hash": "d3fd2899817b6737",
          "publicPath": "/microservices-datadriven/obaas/assets/js/runtime~main.285401bd.js"
        }
      ]
    },
    "380": {
      "js": [
        {
          "file": "assets/js/065e901c.b591831b.js",
          "hash": "ef76f2ec58182b7b",
          "publicPath": "/microservices-datadriven/obaas/assets/js/065e901c.b591831b.js"
        }
      ]
    },
    "381": {
      "js": [
        {
          "file": "assets/js/2779c114.34e96eb9.js",
          "hash": "c2f767a29e92a0f4",
          "publicPath": "/microservices-datadriven/obaas/assets/js/2779c114.34e96eb9.js"
        }
      ]
    },
    "401": {
      "js": [
        {
          "file": "assets/js/17896441.951229dd.js",
          "hash": "bd380d563b97c006",
          "publicPath": "/microservices-datadriven/obaas/assets/js/17896441.951229dd.js"
        }
      ]
    },
    "432": {
      "js": [
        {
          "file": "assets/js/a6d26dbd.d0200ec0.js",
          "hash": "467c168a2a84d05b",
          "publicPath": "/microservices-datadriven/obaas/assets/js/a6d26dbd.d0200ec0.js"
        }
      ]
    },
    "443": {
      "js": [
        {
          "file": "assets/js/a3208752.dab36b07.js",
          "hash": "0c0ebf35800f1ce4",
          "publicPath": "/microservices-datadriven/obaas/assets/js/a3208752.dab36b07.js"
        }
      ]
    },
    "445": {
      "js": [
        {
          "file": "assets/js/74e04c72.567e9033.js",
          "hash": "6dfa31c4fdc14763",
          "publicPath": "/microservices-datadriven/obaas/assets/js/74e04c72.567e9033.js"
        }
      ]
    },
    "490": {
      "js": [
        {
          "file": "assets/js/c85a4240.8a8fa9bf.js",
          "hash": "7e497fda315aa867",
          "publicPath": "/microservices-datadriven/obaas/assets/js/c85a4240.8a8fa9bf.js"
        }
      ]
    },
    "491": {
      "js": [
        {
          "file": "assets/js/642eca8e.74dce339.js",
          "hash": "b427658ac64483f8",
          "publicPath": "/microservices-datadriven/obaas/assets/js/642eca8e.74dce339.js"
        }
      ]
    },
    "501": {
      "js": [
        {
          "file": "assets/js/5014eec9.4f81aa82.js",
          "hash": "c4e494ed615cffbc",
          "publicPath": "/microservices-datadriven/obaas/assets/js/5014eec9.4f81aa82.js"
        }
      ]
    },
    "583": {
      "js": [
        {
          "file": "assets/js/0d502caa.d698656f.js",
          "hash": "1652cf67014df7cb",
          "publicPath": "/microservices-datadriven/obaas/assets/js/0d502caa.d698656f.js"
        }
      ]
    },
    "610": {
      "js": [
        {
          "file": "assets/js/7694d7e1.d7178cbd.js",
          "hash": "7d1f0d6f6d0e7b19",
          "publicPath": "/microservices-datadriven/obaas/assets/js/7694d7e1.d7178cbd.js"
        }
      ]
    },
    "624": {
      "js": [
        {
          "file": "assets/js/c6f57b75.f227a117.js",
          "hash": "966940000e973365",
          "publicPath": "/microservices-datadriven/obaas/assets/js/c6f57b75.f227a117.js"
        }
      ]
    },
    "628": {
      "js": [
        {
          "file": "assets/js/23bbaa4d.82386ad5.js",
          "hash": "d700517ef31a880a",
          "publicPath": "/microservices-datadriven/obaas/assets/js/23bbaa4d.82386ad5.js"
        }
      ]
    },
    "640": {
      "js": [
        {
          "file": "assets/js/76634496.f558edc1.js",
          "hash": "7ff861ad51c9b62f",
          "publicPath": "/microservices-datadriven/obaas/assets/js/76634496.f558edc1.js"
        }
      ]
    },
    "646": {
      "js": [
        {
          "file": "assets/js/a35772e5.8f551e42.js",
          "hash": "c3b6fa833b15aec6",
          "publicPath": "/microservices-datadriven/obaas/assets/js/a35772e5.8f551e42.js"
        }
      ]
    },
    "647": {
      "js": [
        {
          "file": "assets/js/5e95c892.0955054f.js",
          "hash": "e9142f845c082b23",
          "publicPath": "/microservices-datadriven/obaas/assets/js/5e95c892.0955054f.js"
        }
      ]
    },
    "668": {
      "js": [
        {
          "file": "assets/js/668.d9e5e436.js",
          "hash": "c998d8ffbd44298d",
          "publicPath": "/microservices-datadriven/obaas/assets/js/668.d9e5e436.js"
        }
      ]
    },
    "679": {
      "js": [
        {
          "file": "assets/js/1933a263.cdd39115.js",
          "hash": "bce7107b30551b0b",
          "publicPath": "/microservices-datadriven/obaas/assets/js/1933a263.cdd39115.js"
        }
      ]
    },
    "725": {
      "js": [
        {
          "file": "assets/js/f7d327e6.74184bd4.js",
          "hash": "f961104ab141c5e9",
          "publicPath": "/microservices-datadriven/obaas/assets/js/f7d327e6.74184bd4.js"
        }
      ]
    },
    "732": {
      "js": [
        {
          "file": "assets/js/a2ba2a64.d7864a56.js",
          "hash": "89ee2aa1d134eb7f",
          "publicPath": "/microservices-datadriven/obaas/assets/js/a2ba2a64.d7864a56.js"
        }
      ]
    },
    "742": {
      "js": [
        {
          "file": "assets/js/aba21aa0.ef5bd9e3.js",
          "hash": "79f8f3a75020f5cc",
          "publicPath": "/microservices-datadriven/obaas/assets/js/aba21aa0.ef5bd9e3.js"
        }
      ]
    },
    "748": {
      "js": [
        {
          "file": "assets/js/84a15b3e.1f459551.js",
          "hash": "3089b85032dfeb7d",
          "publicPath": "/microservices-datadriven/obaas/assets/js/84a15b3e.1f459551.js"
        }
      ]
    },
    "762": {
      "js": [
        {
          "file": "assets/js/6908b1b0.aa932f5f.js",
          "hash": "749b0a1adc20f9af",
          "publicPath": "/microservices-datadriven/obaas/assets/js/6908b1b0.aa932f5f.js"
        }
      ]
    },
    "771": {
      "js": [
        {
          "file": "assets/js/0fcb4221.88514d07.js",
          "hash": "6c75672e6953b382",
          "publicPath": "/microservices-datadriven/obaas/assets/js/0fcb4221.88514d07.js"
        }
      ]
    },
    "775": {
      "js": [
        {
          "file": "assets/js/f6310cba.bfaa9540.js",
          "hash": "cba42256eb703d66",
          "publicPath": "/microservices-datadriven/obaas/assets/js/f6310cba.bfaa9540.js"
        }
      ]
    },
    "792": {
      "js": [
        {
          "file": "assets/js/main.23bc3bfe.js",
          "hash": "fcabe4cc9cabbae2",
          "publicPath": "/microservices-datadriven/obaas/assets/js/main.23bc3bfe.js"
        }
      ]
    },
    "806": {
      "js": [
        {
          "file": "assets/js/b420b19e.d9a9afe5.js",
          "hash": "e8d2f7774ff3380e",
          "publicPath": "/microservices-datadriven/obaas/assets/js/b420b19e.d9a9afe5.js"
        }
      ]
    },
    "818": {
      "js": [
        {
          "file": "assets/js/74f6f9f9.9f561a9c.js",
          "hash": "1804d0172d82bf14",
          "publicPath": "/microservices-datadriven/obaas/assets/js/74f6f9f9.9f561a9c.js"
        }
      ]
    },
    "845": {
      "js": [
        {
          "file": "assets/js/6b1ba41c.aa1aaa78.js",
          "hash": "2cfe6e63a1aee5d6",
          "publicPath": "/microservices-datadriven/obaas/assets/js/6b1ba41c.aa1aaa78.js"
        }
      ]
    },
    "869": {
      "css": [
        {
          "file": "assets/css/styles.d61b3bcc.css",
          "hash": "a371057cbb491b69",
          "publicPath": "/microservices-datadriven/obaas/assets/css/styles.d61b3bcc.css"
        }
      ]
    },
    "882": {
      "js": [
        {
          "file": "assets/js/c2a49136.ff568b44.js",
          "hash": "48948c0739875c0e",
          "publicPath": "/microservices-datadriven/obaas/assets/js/c2a49136.ff568b44.js"
        }
      ]
    },
    "964": {
      "js": [
        {
          "file": "assets/js/1df93b7f.83d023b6.js",
          "hash": "dc5116f5f1101de3",
          "publicPath": "/microservices-datadriven/obaas/assets/js/1df93b7f.83d023b6.js"
        }
      ]
    },
    "969": {
      "js": [
        {
          "file": "assets/js/14eb3368.d64fc15c.js",
          "hash": "e702ad6135b2bd57",
          "publicPath": "/microservices-datadriven/obaas/assets/js/14eb3368.d64fc15c.js"
        }
      ]
    },
    "976": {
      "js": [
        {
          "file": "assets/js/0e384e19.4c9f6f28.js",
          "hash": "de3b7300f545027d",
          "publicPath": "/microservices-datadriven/obaas/assets/js/0e384e19.4c9f6f28.js"
        }
      ]
    },
    "994": {
      "js": [
        {
          "file": "assets/js/6245a28e.42fea334.js",
          "hash": "febfe7b039b88e82",
          "publicPath": "/microservices-datadriven/obaas/assets/js/6245a28e.42fea334.js"
        }
      ]
    }
  }
}